g42cloudsdkces/__init__.py
g42cloudsdkces/v1/__init__.py
g42cloudsdkces/v1/ces_async_client.py
g42cloudsdkces/v1/ces_client.py
g42cloudsdkces/v1/model/__init__.py
g42cloudsdkces/v1/model/additional_info.py
g42cloudsdkces/v1/model/alarm_actions.py
g42cloudsdkces/v1/model/alarm_history_info.py
g42cloudsdkces/v1/model/alarm_template.py
g42cloudsdkces/v1/model/alarm_template_condition.py
g42cloudsdkces/v1/model/batch_list_metric_data_request.py
g42cloudsdkces/v1/model/batch_list_metric_data_request_body.py
g42cloudsdkces/v1/model/batch_list_metric_data_response.py
g42cloudsdkces/v1/model/batch_metric_data.py
g42cloudsdkces/v1/model/condition.py
g42cloudsdkces/v1/model/create_alarm_request.py
g42cloudsdkces/v1/model/create_alarm_request_body.py
g42cloudsdkces/v1/model/create_alarm_response.py
g42cloudsdkces/v1/model/create_alarm_template_request.py
g42cloudsdkces/v1/model/create_alarm_template_request_body.py
g42cloudsdkces/v1/model/create_alarm_template_response.py
g42cloudsdkces/v1/model/create_events_request.py
g42cloudsdkces/v1/model/create_events_response.py
g42cloudsdkces/v1/model/create_events_response_body.py
g42cloudsdkces/v1/model/create_metric_data_request.py
g42cloudsdkces/v1/model/create_metric_data_response.py
g42cloudsdkces/v1/model/create_resource_group.py
g42cloudsdkces/v1/model/create_resource_group_request.py
g42cloudsdkces/v1/model/create_resource_group_request_body.py
g42cloudsdkces/v1/model/create_resource_group_response.py
g42cloudsdkces/v1/model/data_point_for_alarm_history.py
g42cloudsdkces/v1/model/datapoint.py
g42cloudsdkces/v1/model/datapoint_for_batch_metric.py
g42cloudsdkces/v1/model/delete_alarm_request.py
g42cloudsdkces/v1/model/delete_alarm_response.py
g42cloudsdkces/v1/model/delete_alarm_template_request.py
g42cloudsdkces/v1/model/delete_alarm_template_response.py
g42cloudsdkces/v1/model/delete_resource_group_request.py
g42cloudsdkces/v1/model/delete_resource_group_response.py
g42cloudsdkces/v1/model/event_data_info.py
g42cloudsdkces-0.0.10b0.dist-info/LICENSE
g42cloudsdkces-0.0.10b0.dist-info/METADATA
g42cloudsdkces-0.0.10b0.dist-info/WHEEL
g42cloudsdkces-0.0.10b0.dist-info/top_level.txt
g42cloudsdkces-0.0.10b0.dist-info/RECORD
